myst/__init__.py
time_array/__init__.py
time_array-0.0.1.dist-info/LICENSE
time_array-0.0.1.dist-info/METADATA
time_array-0.0.1.dist-info/WHEEL
time_array-0.0.1.dist-info/top_level.txt
time_array-0.0.1.dist-info/RECORD
