Metadata-Version: 2.1
Name: time-array
Version: 0.0.1
Summary: coming soon
Home-page: https://myst.ai
Author: Sean MacPherson
Author-email: smacpherson@myst.ai
License: UNKNOWN
Platform: UNKNOWN
